.readthedocs.yaml
AUTHORS
ChangeLog
LICENSE.txt
README.rst
format_code.sh
requirements.txt
setup.cfg
setup.py
test.py
doc/conf.py
doc/index.rst
doc/api/index.rst
doc/api/pyffs.conv.rst
doc/api/pyffs.czt.rst
doc/api/pyffs.ffs.rst
doc/api/pyffs.func.rst
doc/api/pyffs.interp.rst
doc/api/pyffs.util.rst
doc/theory/CZT.rst
doc/theory/DFT.rst
doc/theory/FS_eval_for_BL_signals.rst
doc/theory/func_interpolation_BL_signals.rst
doc/theory/index.rst
examples/convolve_1d.py
examples/convolve_2d.py
examples/ffs_1d.py
examples/ffs_2d.py
examples/interp_1d.py
examples/interp_2d.py
examples/util.py
profile/bandlimited_interp1d_vary_M.py
profile/bandlimited_interp1d_vary_width.py
profile/bandlimited_interp2d_vary_M.py
profile/bandlimited_interp2d_vary_width.py
profile/convolve2d.py
profile/ffs.py
profile/ffsn.py
profile/fs_interp1d_vary_M.py
profile/fs_interp1d_vary_NFS.py
profile/fs_interp2d_vary_M.py
profile/fs_interp2d_vary_NFS.py
profile/util.py
pyFFS.egg-info/PKG-INFO
pyFFS.egg-info/SOURCES.txt
pyFFS.egg-info/dependency_links.txt
pyFFS.egg-info/pbr.json
pyFFS.egg-info/requires.txt
pyFFS.egg-info/top_level.txt
pyFFS.egg-info/zip-safe
pyffs/__init__.py
pyffs/backend.py
pyffs/conv.py
pyffs/czt.py
pyffs/ffs.py
pyffs/func.py
pyffs/interp.py
pyffs/util.py
test/test_czt.py
test/test_ffs.py
test/test_interp.py
test/test_util.py