Metadata-Version: 2.1
Name: pyFFS
Version: 2.2.3
Summary: Fast Fourier Series library
Home-page: https://github.com/imagingofthings/pyFFS
Author: Sepand KASHANI, Eric BEZZAM, Matthieu SIMEONI
Author-email: kashani.sepand@gmail.com
License: BSD
Download-URL: https://github.com/imagingofthings/pyFFS
Platform: UNKNOWN
Classifier: Development Status :: 5 - Production/Stable
Classifier: Intended Audience :: Science/Research
Classifier: License :: OSI Approved :: BSD License
Classifier: Programming Language :: Python :: 3
Classifier: Programming Language :: Python :: Implementation :: CPython
Classifier: Topic :: Scientific/Engineering
Requires-Python: >=3.6
Provides-Extra: dev
Provides-Extra: cuda110
